{
  "updated": "2026-06-20T06:20:59-03:00",
  "location": {
    "id": 1840,
    "name": "El Calafate",
    "department": null,
    "province": "Santa Cruz",
    "lat": -50.34061394,
    "lon": -72.26842674
  },
  "type": "location",
  "forecast": [
    {
      "date": "2026-06-20",
      "temp_min": -1.0,
      "temp_max": 5.0,
      "humidity_min": 88.0,
      "humidity_max": 94.0,
      "early_morning": null,
      "morning": null,
      "afternoon": {
        "humidity": 88.0,
        "rain_prob_range": [
          10,
          40
        ],
        "gust_range": [
          51,
          59
        ],
        "temperature": 5.0,
        "visibility": "Regular",
        "rain06h": 0.6,
        "weather": {
          "description": "Lluvias y nevadas",
          "id": 77
        },
        "wind": {
          "direction": "NO",
          "deg": 315.0,
          "speed_range": [
            23,
            31
          ]
        },
        "river": null,
        "border": null
      },
      "night": {
        "humidity": 90.0,
        "rain_prob_range": [
          10,
          40
        ],
        "gust_range": [
          42,
          50
        ],
        "temperature": 0.0,
        "visibility": "Mala",
        "rain06h": 0.0,
        "weather": {
          "description": "Nevadas",
          "id": 79
        },
        "wind": {
          "direction": "SO",
          "deg": 225.0,
          "speed_range": [
            23,
            31
          ]
        },
        "river": null,
        "border": null
      }
    },
    {
      "date": "2026-06-21",
      "temp_min": -1.0,
      "temp_max": 5.0,
      "humidity_min": 63.0,
      "humidity_max": 83.0,
      "early_morning": {
        "humidity": 70.0,
        "rain_prob_range": [
          0,
          0
        ],
        "gust_range": null,
        "temperature": 0.0,
        "visibility": "Buena",
        "rain06h": 0.0,
        "weather": {
          "description": "Parcialmente nublado",
          "id": 25
        },
        "wind": {
          "direction": "SO",
          "deg": 225.0,
          "speed_range": [
            23,
            31
          ]
        },
        "river": null,
        "border": null
      },
      "morning": {
        "humidity": 83.0,
        "rain_prob_range": [
          0,
          0
        ],
        "gust_range": null,
        "temperature": -1.0,
        "visibility": "Buena",
        "rain06h": 0.0,
        "weather": {
          "description": "Parcialmente nublado",
          "id": 25
        },
        "wind": {
          "direction": "O",
          "deg": 270.0,
          "speed_range": [
            13,
            22
          ]
        },
        "river": null,
        "border": null
      },
      "afternoon": {
        "humidity": 63.0,
        "rain_prob_range": [
          0,
          0
        ],
        "gust_range": [
          51,
          59
        ],
        "temperature": 5.0,
        "visibility": "Buena",
        "rain06h": 0.0,
        "weather": {
          "description": "Parcialmente nublado",
          "id": 25
        },
        "wind": {
          "direction": "O",
          "deg": 292.5,
          "speed_range": [
            23,
            31
          ]
        },
        "river": null,
        "border": null
      },
      "night": {
        "humidity": 68.0,
        "rain_prob_range": [
          0,
          0
        ],
        "gust_range": null,
        "temperature": 1.0,
        "visibility": "Buena",
        "rain06h": 0.0,
        "weather": {
          "description": "Parcialmente nublado",
          "id": 25
        },
        "wind": {
          "direction": "O",
          "deg": 292.5,
          "speed_range": [
            23,
            31
          ]
        },
        "river": null,
        "border": null
      }
    },
    {
      "date": "2026-06-22",
      "temp_min": -2.0,
      "temp_max": 6.0,
      "humidity_min": 64.0,
      "humidity_max": 71.0,
      "early_morning": null,
      "morning": {
        "humidity": 71.0,
        "rain_prob_range": [
          0,
          10
        ],
        "gust_range": [
          60,
          69
        ],
        "temperature": -2.0,
        "visibility": "Buena",
        "rain06h": 0.0,
        "weather": {
          "description": "Mayormente nublado",
          "id": 37
        },
        "wind": {
          "direction": "O",
          "deg": 270.0,
          "speed_range": [
            32,
            41
          ]
        },
        "river": null,
        "border": null
      },
      "afternoon": {
        "humidity": 64.0,
        "rain_prob_range": [
          10,
          40
        ],
        "gust_range": [
          60,
          69
        ],
        "temperature": 6.0,
        "visibility": "Regular",
        "rain06h": 0.0,
        "weather": {
          "description": "Lluvias y nevadas",
          "id": 77
        },
        "wind": {
          "direction": "O",
          "deg": 270.0,
          "speed_range": [
            32,
            41
          ]
        },
        "river": null,
        "border": null
      },
      "night": null
    },
    {
      "date": "2026-06-23",
      "temp_min": -1.0,
      "temp_max": 4.0,
      "humidity_min": 66.0,
      "humidity_max": 68.0,
      "early_morning": null,
      "morning": {
        "humidity": 68.0,
        "rain_prob_range": [
          0,
          0
        ],
        "gust_range": [
          60,
          69
        ],
        "temperature": -1.0,
        "visibility": "Buena",
        "rain06h": 0.0,
        "weather": {
          "description": "Mayormente nublado",
          "id": 37
        },
        "wind": {
          "direction": "SO",
          "deg": 247.5,
          "speed_range": [
            13,
            22
          ]
        },
        "river": null,
        "border": null
      },
      "afternoon": {
        "humidity": 66.0,
        "rain_prob_range": [
          0,
          10
        ],
        "gust_range": [
          60,
          69
        ],
        "temperature": 4.0,
        "visibility": "Buena",
        "rain06h": 0.0,
        "weather": {
          "description": "Mayormente nublado",
          "id": 37
        },
        "wind": {
          "direction": "NO",
          "deg": 315.0,
          "speed_range": [
            13,
            22
          ]
        },
        "river": null,
        "border": null
      },
      "night": null
    },
    {
      "date": "2026-06-24",
      "temp_min": -1.0,
      "temp_max": 5.0,
      "humidity_min": 94.0,
      "humidity_max": 97.0,
      "early_morning": null,
      "morning": {
        "humidity": 97.0,
        "rain_prob_range": [
          0,
          10
        ],
        "gust_range": [
          60,
          69
        ],
        "temperature": -1.0,
        "visibility": "Buena",
        "rain06h": 0.8,
        "weather": {
          "description": "Mayormente nublado",
          "id": 37
        },
        "wind": {
          "direction": "SO",
          "deg": 247.5,
          "speed_range": [
            23,
            31
          ]
        },
        "river": null,
        "border": null
      },
      "afternoon": {
        "humidity": 94.0,
        "rain_prob_range": [
          0,
          0
        ],
        "gust_range": [
          60,
          69
        ],
        "temperature": 5.0,
        "visibility": "Buena",
        "rain06h": 0.2,
        "weather": {
          "description": "Mayormente nublado",
          "id": 37
        },
        "wind": {
          "direction": "SO",
          "deg": 247.5,
          "speed_range": [
            23,
            31
          ]
        },
        "river": null,
        "border": null
      },
      "night": null
    },
    {
      "date": "2026-06-25",
      "temp_min": -1.0,
      "temp_max": 5.0,
      "humidity_min": 85.0,
      "humidity_max": 89.0,
      "early_morning": null,
      "morning": {
        "humidity": 89.0,
        "rain_prob_range": [
          0,
          10
        ],
        "gust_range": null,
        "temperature": -1.0,
        "visibility": "Buena",
        "rain06h": 0.0,
        "weather": {
          "description": "Mayormente nublado",
          "id": 37
        },
        "wind": {
          "direction": "NO",
          "deg": 315.0,
          "speed_range": [
            13,
            22
          ]
        },
        "river": null,
        "border": null
      },
      "afternoon": {
        "humidity": 85.0,
        "rain_prob_range": [
          0,
          10
        ],
        "gust_range": null,
        "temperature": 5.0,
        "visibility": "Buena",
        "rain06h": 0.0,
        "weather": {
          "description": "Mayormente nublado",
          "id": 37
        },
        "wind": {
          "direction": "NO",
          "deg": 315.0,
          "speed_range": [
            13,
            22
          ]
        },
        "river": null,
        "border": null
      },
      "night": null
    },
    {
      "date": "2026-06-26",
      "temp_min": 0.0,
      "temp_max": 7.0,
      "humidity_min": 61.0,
      "humidity_max": 76.0,
      "early_morning": null,
      "morning": {
        "humidity": 76.0,
        "rain_prob_range": [
          0,
          10
        ],
        "gust_range": [
          60,
          69
        ],
        "temperature": 0.0,
        "visibility": "Buena",
        "rain06h": 0.0,
        "weather": {
          "description": "Mayormente nublado",
          "id": 37
        },
        "wind": {
          "direction": "O",
          "deg": 270.0,
          "speed_range": [
            32,
            41
          ]
        },
        "river": null,
        "border": null
      },
      "afternoon": {
        "humidity": 61.0,
        "rain_prob_range": [
          0,
          10
        ],
        "gust_range": [
          60,
          69
        ],
        "temperature": 7.0,
        "visibility": "Buena",
        "rain06h": 0.0,
        "weather": {
          "description": "Mayormente nublado",
          "id": 37
        },
        "wind": {
          "direction": "O",
          "deg": 292.5,
          "speed_range": [
            32,
            41
          ]
        },
        "river": null,
        "border": null
      },
      "night": null
    }
  ],
  "source_location": {
    "id": 1840,
    "name": "El Calafate",
    "department": "Lago Argentino",
    "province": "Santa Cruz",
    "type": "Localidad",
    "coord": {
      "lon": -72.2684,
      "lat": -50.3406
    }
  },
  "catalog_location": {
    "id": 1840,
    "name": "El Calafate",
    "department": null,
    "province": "Santa Cruz",
    "lat": -50.34061394,
    "lon": -72.26842674,
    "area": null,
    "station_name": null,
    "station_number": 87904,
    "forecast_reference_id": 1840,
    "forecast_location_id": 1840,
    "used_reference": false
  },
  "data_status": "forecast_available",
  "forecast_source_type": "ws1_current_api",
  "source": "Servicio Meteorológico Nacional",
  "source_url": "https://ws1.smn.gob.ar/v1/forecast/location/1840",
  "generated_at": "2026-06-20T19:57:10.840698+00:00"
}
