{
  "updated": "2026-06-29T05:46:05-03:00",
  "location": {
    "id": 5648,
    "name": "Resistencia",
    "department": null,
    "province": "Chaco",
    "lat": -27.45546341,
    "lon": -58.99566269
  },
  "type": "location",
  "forecast": [
    {
      "date": "2026-06-29",
      "temp_min": 10.0,
      "temp_max": 17.0,
      "humidity_min": 46.0,
      "humidity_max": 94.0,
      "early_morning": null,
      "morning": {
        "humidity": 90.0,
        "rain_prob_range": [
          0,
          0
        ],
        "gust_range": null,
        "temperature": 10.0,
        "visibility": "Buena",
        "rain06h": 0.1,
        "weather": {
          "description": "Parcialmente nublado",
          "id": 25
        },
        "wind": {
          "direction": "E",
          "deg": 112.5,
          "speed_range": [
            7,
            12
          ]
        },
        "river": null,
        "border": null
      },
      "afternoon": {
        "humidity": 46.0,
        "rain_prob_range": [
          0,
          0
        ],
        "gust_range": null,
        "temperature": 17.0,
        "visibility": "Buena",
        "rain06h": 0.0,
        "weather": {
          "description": "Parcialmente nublado",
          "id": 25
        },
        "wind": {
          "direction": "E",
          "deg": 112.5,
          "speed_range": [
            7,
            12
          ]
        },
        "river": null,
        "border": null
      },
      "night": {
        "humidity": 80.0,
        "rain_prob_range": [
          0,
          0
        ],
        "gust_range": null,
        "temperature": 11.0,
        "visibility": "Buena",
        "rain06h": 0.0,
        "weather": {
          "description": "Parcialmente nublado",
          "id": 25
        },
        "wind": {
          "direction": "SE",
          "deg": 157.5,
          "speed_range": [
            7,
            12
          ]
        },
        "river": null,
        "border": null
      }
    },
    {
      "date": "2026-06-30",
      "temp_min": 8.0,
      "temp_max": 16.0,
      "humidity_min": 55.0,
      "humidity_max": 79.0,
      "early_morning": {
        "humidity": 77.0,
        "rain_prob_range": [
          0,
          0
        ],
        "gust_range": null,
        "temperature": 10.0,
        "visibility": "Buena",
        "rain06h": 0.0,
        "weather": {
          "description": "Mayormente nublado",
          "id": 37
        },
        "wind": {
          "direction": "SE",
          "deg": 157.5,
          "speed_range": [
            7,
            12
          ]
        },
        "river": null,
        "border": null
      },
      "morning": {
        "humidity": 79.0,
        "rain_prob_range": [
          0,
          0
        ],
        "gust_range": null,
        "temperature": 8.0,
        "visibility": "Buena",
        "rain06h": 0.0,
        "weather": {
          "description": "Mayormente nublado",
          "id": 37
        },
        "wind": {
          "direction": "NE",
          "deg": 67.5,
          "speed_range": [
            7,
            12
          ]
        },
        "river": null,
        "border": null
      },
      "afternoon": {
        "humidity": 55.0,
        "rain_prob_range": [
          0,
          10
        ],
        "gust_range": null,
        "temperature": 16.0,
        "visibility": "Buena",
        "rain06h": 0.0,
        "weather": {
          "description": "Parcialmente nublado",
          "id": 25
        },
        "wind": {
          "direction": "NE",
          "deg": 67.5,
          "speed_range": [
            13,
            22
          ]
        },
        "river": null,
        "border": null
      },
      "night": {
        "humidity": 75.0,
        "rain_prob_range": [
          0,
          10
        ],
        "gust_range": null,
        "temperature": 11.0,
        "visibility": "Buena",
        "rain06h": 0.0,
        "weather": {
          "description": "Mayormente nublado",
          "id": 37
        },
        "wind": {
          "direction": "E",
          "deg": 112.5,
          "speed_range": [
            7,
            12
          ]
        },
        "river": null,
        "border": null
      }
    },
    {
      "date": "2026-07-01",
      "temp_min": 8.0,
      "temp_max": 17.0,
      "humidity_min": 78.0,
      "humidity_max": 94.0,
      "early_morning": null,
      "morning": {
        "humidity": 94.0,
        "rain_prob_range": [
          10,
          40
        ],
        "gust_range": null,
        "temperature": 8.0,
        "visibility": "Regular",
        "rain06h": 0.1,
        "weather": {
          "description": "Chaparrones",
          "id": 74
        },
        "wind": {
          "direction": "SE",
          "deg": 157.5,
          "speed_range": [
            7,
            12
          ]
        },
        "river": null,
        "border": null
      },
      "afternoon": {
        "humidity": 78.0,
        "rain_prob_range": [
          10,
          40
        ],
        "gust_range": null,
        "temperature": 17.0,
        "visibility": "Regular",
        "rain06h": 0.0,
        "weather": {
          "description": "Chaparrones",
          "id": 74
        },
        "wind": {
          "direction": "S",
          "deg": 202.5,
          "speed_range": [
            13,
            22
          ]
        },
        "river": null,
        "border": null
      },
      "night": null
    },
    {
      "date": "2026-07-02",
      "temp_min": 11.0,
      "temp_max": 16.0,
      "humidity_min": 87.0,
      "humidity_max": 96.0,
      "early_morning": null,
      "morning": {
        "humidity": 96.0,
        "rain_prob_range": [
          0,
          10
        ],
        "gust_range": null,
        "temperature": 11.0,
        "visibility": "Buena",
        "rain06h": 0.2,
        "weather": {
          "description": "Mayormente nublado",
          "id": 37
        },
        "wind": {
          "direction": "S",
          "deg": 202.5,
          "speed_range": [
            13,
            22
          ]
        },
        "river": null,
        "border": null
      },
      "afternoon": {
        "humidity": 87.0,
        "rain_prob_range": [
          0,
          0
        ],
        "gust_range": null,
        "temperature": 16.0,
        "visibility": "Buena",
        "rain06h": 0.1,
        "weather": {
          "description": "Ligeramente nublado",
          "id": 13
        },
        "wind": {
          "direction": "S",
          "deg": 202.5,
          "speed_range": [
            13,
            22
          ]
        },
        "river": null,
        "border": null
      },
      "night": null
    },
    {
      "date": "2026-07-03",
      "temp_min": 5.0,
      "temp_max": 15.0,
      "humidity_min": 69.0,
      "humidity_max": 83.0,
      "early_morning": null,
      "morning": {
        "humidity": 69.0,
        "rain_prob_range": [
          0,
          0
        ],
        "gust_range": null,
        "temperature": 5.0,
        "visibility": "Buena",
        "rain06h": 0.0,
        "weather": {
          "description": "Parcialmente nublado",
          "id": 25
        },
        "wind": {
          "direction": "S",
          "deg": 180.0,
          "speed_range": [
            7,
            12
          ]
        },
        "river": null,
        "border": null
      },
      "afternoon": {
        "humidity": 83.0,
        "rain_prob_range": [
          0,
          0
        ],
        "gust_range": null,
        "temperature": 15.0,
        "visibility": "Buena",
        "rain06h": 0.0,
        "weather": {
          "description": "Parcialmente nublado",
          "id": 25
        },
        "wind": {
          "direction": "NE",
          "deg": 67.5,
          "speed_range": [
            13,
            22
          ]
        },
        "river": null,
        "border": null
      },
      "night": null
    },
    {
      "date": "2026-07-04",
      "temp_min": 2.0,
      "temp_max": 16.0,
      "humidity_min": 52.0,
      "humidity_max": 84.0,
      "early_morning": null,
      "morning": {
        "humidity": 84.0,
        "rain_prob_range": [
          0,
          0
        ],
        "gust_range": null,
        "temperature": 2.0,
        "visibility": "Buena",
        "rain06h": 0.0,
        "weather": {
          "description": "Parcialmente nublado",
          "id": 25
        },
        "wind": {
          "direction": "NE",
          "deg": 45.0,
          "speed_range": [
            13,
            22
          ]
        },
        "river": null,
        "border": null
      },
      "afternoon": {
        "humidity": 52.0,
        "rain_prob_range": [
          0,
          0
        ],
        "gust_range": null,
        "temperature": 16.0,
        "visibility": "Buena",
        "rain06h": 0.0,
        "weather": {
          "description": "Parcialmente nublado",
          "id": 25
        },
        "wind": {
          "direction": "NE",
          "deg": 45.0,
          "speed_range": [
            13,
            22
          ]
        },
        "river": null,
        "border": null
      },
      "night": null
    },
    {
      "date": "2026-07-05",
      "temp_min": 7.0,
      "temp_max": 18.0,
      "humidity_min": 59.0,
      "humidity_max": 59.0,
      "early_morning": null,
      "morning": {
        "humidity": null,
        "rain_prob_range": [
          0,
          0
        ],
        "gust_range": null,
        "temperature": 7.0,
        "visibility": "Buena",
        "rain06h": null,
        "weather": {
          "description": "Ligeramente nublado",
          "id": 13
        },
        "wind": {
          "direction": "SO",
          "deg": 225.0,
          "speed_range": [
            0,
            2
          ]
        },
        "river": null,
        "border": null
      },
      "afternoon": {
        "humidity": 59.0,
        "rain_prob_range": [
          0,
          0
        ],
        "gust_range": null,
        "temperature": 18.0,
        "visibility": "Buena",
        "rain06h": 0.0,
        "weather": {
          "description": "Mayormente nublado",
          "id": 37
        },
        "wind": {
          "direction": "S",
          "deg": 202.5,
          "speed_range": [
            7,
            12
          ]
        },
        "river": null,
        "border": null
      },
      "night": null
    }
  ],
  "source_location": {
    "id": 5648,
    "name": "Resistencia",
    "department": "San Fernando",
    "province": "Chaco",
    "type": "Ciudad",
    "coord": {
      "lon": -58.9957,
      "lat": -27.4555
    }
  },
  "catalog_location": {
    "id": 5648,
    "name": "Resistencia",
    "department": null,
    "province": "Chaco",
    "lat": -27.45546341,
    "lon": -58.99566269,
    "area": null,
    "station_name": null,
    "station_number": 87155,
    "forecast_reference_id": 5648,
    "forecast_location_id": 5648,
    "used_reference": false
  },
  "data_status": "forecast_available",
  "forecast_source_type": "ws1_current_api",
  "source": "Servicio Meteorológico Nacional",
  "source_url": "https://ws1.smn.gob.ar/v1/forecast/location/5648",
  "generated_at": "2026-06-29T13:31:14.151923+00:00"
}
